filark/__init__.py
filark/algorithms/__init__.py
filark/dsp/__init__.py
filark/dsp/base.py
filark/dsp/fk.py
filark/dsp/spatial.py
filark/dsp/temporal.py
filark/explore/__init__.py
filark/gui/__init__.py
filark/gui/app.py
filark/gui/display_model.py
filark/gui/main_window.py
filark/gui/modules/__init__.py
filark/gui/modules/algorithms.py
filark/gui/modules/analysis.py
filark/gui/modules/annotation.py
filark/gui/modules/load.py
filark/gui/modules/visuals.py
filark/gui/roi/__init__.py
filark/gui/roi/roi_window.py
filark/gui/roi/views/__init__.py
filark/gui/roi/views/fk_view.py
filark/gui/styles/__init__.py
filark/gui/styles/dark.qss
filark/gui/styles/light.qss
filark/gui/widgets/__init__.py
filark/gui/widgets/navbar.py
filark/gui/widgets/sliding_drawer.py
filark/gui/widgets/typography.py
filark/io/__init__.py
filark/io/fileset.py
filark/io/h5io.py
filark/io/protocols.py
filark/io/streaming.py
filark/pipeline/__init__.py
filark/processing/__init__.py
filark/utils/__init__.py
filark/viz/__init__.py
filark/viz/_canvas_mixin.py
filark/viz/axis.py
filark/viz/camera.py
filark/viz/canvas.py
filark/viz/image.py
filark/viz/scheduler.py
filark-0.0.1.dist-info/licenses/LICENSE
filark-0.0.1.dist-info/METADATA
filark-0.0.1.dist-info/WHEEL
filark-0.0.1.dist-info/entry_points.txt
filark-0.0.1.dist-info/top_level.txt
filark-0.0.1.dist-info/RECORD
