Metadata-Version: 2.4
Name: filark
Version: 0.0.1
Summary: High-performance DAS visualization and analysis tool
Author-email: Jintao Li <lijintaobt@gmail.com>
License: MIT
Project-URL: Homepage, https://github.com/JintaoLee-Roger/filark
Keywords: visualization,geophysics,DAS,Fiber
Requires-Python: >=3.9
License-File: LICENSE
Requires-Dist: numpy
Requires-Dist: matplotlib
Requires-Dist: vispy
Requires-Dist: PySide6
Requires-Dist: h5py
Requires-Dist: scipy
Dynamic: license-file
